bitty.py
bitty-0.4.1.dist-info/DESCRIPTION.rst
bitty-0.4.1.dist-info/METADATA
bitty-0.4.1.dist-info/pydist.json
bitty-0.4.1.dist-info/RECORD
bitty-0.4.1.dist-info/top_level.txt
bitty-0.4.1.dist-info/WHEEL
