Metadata-Version: 2.0
Name: bitty
Version: 0.4.1
Summary: A tiny database layer. Serious Python Programmers(tm) with Enterprise Requirements need not apply.
Home-page: http://github.com/toastdriven/bitty
Author: Daniel Lindsley
Author-email: daniel@toastdriven.com
License: BSD
Platform: UNKNOWN
Classifier: Intended Audience :: Developers
Classifier: License :: OSI Approved :: BSD License
Classifier: Operating System :: OS Independent
Classifier: Programming Language :: Python
Classifier: Topic :: Utilities
